preamble/__init__.py
preamble/preamble_core.py
preamble/preamble_nemo.py
preamble-0.0.4.dist-info/METADATA
preamble-0.0.4.dist-info/WHEEL
preamble-0.0.4.dist-info/licenses/LICENSE
preamble-0.0.4.dist-info/RECORD
