Metadata-Version: 2.1
Name: preamble
Version: 0.0.4
Summary: APIs for connecting to the preamble.com AI safety backend
Project-URL: Homepage, https://github.com/preambleai/preamble_pypi
Project-URL: Bug Tracker, https://github.com/preambleai/preamble_pypi/issues
Author-email: Jonathan Cefalu <jon@preamble.com>
License-File: LICENSE
Classifier: License :: OSI Approved :: MIT License
Classifier: Operating System :: OS Independent
Classifier: Programming Language :: Python :: 3
Requires-Python: >=3.7
